monkey_coder_sdk/__init__.py
monkey_coder_sdk/client.py
monkey_coder_sdk/helpers.py
monkey_coder_sdk/types.py
monkey_coder_sdk-1.1.0.dist-info/METADATA
monkey_coder_sdk-1.1.0.dist-info/WHEEL
monkey_coder_sdk-1.1.0.dist-info/entry_points.txt
monkey_coder_sdk-1.1.0.dist-info/top_level.txt
monkey_coder_sdk-1.1.0.dist-info/RECORD
